Workbook

Sheet Данные
A1: ID_высказывания | B1: ID_исходного_блока | C1: Текст_высказывания | D1: НОРМА_442ФЗ | E1: КОНКУРС_ПРОЦЕДУРЫ | F1: ТАРИФЫ_НОРМАТИВЫ | G1: РЕЕСТР_ПОСТАВЩИКОВ | H1: ГАРАНТИИ_ОБЪЕМОВ | I1: ОБУЧЕНИЕ_НКО | J1: ИНФОРМАЦИЯ_ПРОЗРАЧНОСТЬ | K1: ИНСТИТУТЫ_ПОДДЕРЖКИ | L1: МУНИЦИПАЛЬНЫЙ_УРОВЕНЬ | M1: КОНКУРЕНЦИЯ_АНТИМОНОПОЛИЯ | N1: ТОНИЧЕСКИЙ_ПОЗИТИВ | O1: ТОНИЧЕСКИЙ_НЕГАТИВ | P1: ТОНИЧЕСКИЙ_СОМНЕНИЕ
A2: 1 | B2: 1 | C2: Каждая, выдаваемая ИППСУ, должна быть "просчитана" и обеспечена средствами со стороны РОИВ на ее реализацию (причем не должны ставиться в приоритет гос. поставщики, поскольку каждый гражданин имеет право выбора поставщика в соответствии с 18 пунктом ИППСУ) | D2: 0 | E2: 0 | F2: 0 | G2: 0 | H2: 0 | I2: 0 | J2: 0 | K2: 0 | L2: 0 | M2: 0 | N2: 0 | O2: 1 | P2: 0
A3: 2 | B3: 2 | C3: Фильтр реестра поставщиков социальных услуг (РОИВ должен исходить из опыта работы кандидата | D3: 0 | E3: 0 | F3: 0 | G3: 1 | H3: 0 | I3: 0 | J3: 0 | K3: 0 | L3: 0 | M3: 0 | N3: 0 | O3: 1 | P3: 0
A4: 3 | B4: 3 | C4: организации) | D4: 0 | E4: 0 | F4: 0 | G4: 0 | H4: 0 | I4: 0 | J4: 0 | K4: 0 | L4: 0 | M4: 0 | N4: 0 | O4: 0 | P4: 1
A5: 4 | B5: 4 | C5: Четкое разделение финансовых обязательств (не должно быть задвоения финансирования одной организации). - | D5: 0 | E5: 0 | F5: 0 | G5: 0 | H5: 1 | I5: 0 | J5: 0 | K5: 0 | L5: 0 | M5: 0 | N5: 0 | O5: 1 | P5: 0
A6: 5 | B6: 5 | C6: отменить установленные лимиты, оказывать соц услуги по потребности нуждающихся | D6: 0 | E6: 0 | F6: 0 | G6: 0 | H6: 1 | I6: 0 | J6: 0 | K6: 0 | L6: 0 | M6: 0 | N6: 0 | O6: 1 | P6: 0
A7: 6 | B7: 6 | C7: не урезать объём и количество соц услуг в ИППСУ | D7: 0 | E7: 0 | F7: 0 | G7: 0 | H7: 1 | I7: 0 | J7: 0 | K7: 0 | L7: 0 | M7: 0 | N7: 0 | O7: 1 | P7: 0
A8: 7 | B8: 7 | C8: предоставлять возможность получать соц услуги детям с ОВЗ и инвалидностью на протяжении всего времени когда есть потребность в соц услугах, сейчас введено ограничение | D8: 0 | E8: 0 | F8: 0 | G8: 0 | H8: 0 | I8: 0 | J8: 0 | K8: 0 | L8: 0 | M8: 0 | N8: 0 | O8: 1 | P8: 0
A9: 8 | B9: 8 | C9: ребенок может пройти только два курса реабилитации в год по ИППСУ, это ограничивает его права на доступную социальную помощь | D9: 0 | E9: 0 | F9: 0 | G9: 0 | H9: 0 | I9: 0 | J9: 0 | K9: 0 | L9: 0 | M9: 0 | N9: 0 | O9: 1 | P9: 0
A10: 9 | B10: 9 | C10: предоставлять ИППСУ нуждающимся детям с 0 лет, сейчас введено ограничение ребенок с ОВЗ и инвалидностью может получи | D10: 0 | E10: 0 | F10: 0 | G10: 0 | H10: 0 | I10: 0 | J10: 0 | K10: 0 | L10: 0 | M10: 0 | N10: 0 | O10: 1 | P10: 0
A11: 10 | B11: 10 | C11: Прозрачные правила вступления и работы в системе социального обслуживания для негосударственных поставщиков | D11: 0 | E11: 0 | F11: 0 | G11: 0 | H11: 0 | I11: 0 | J11: 1 | K11: 0 | L11: 0 | M11: 0 | N11: 0 | O11: 1 | P11: 0
A12: 11 | B12: 11 | C12: Равные условия финансирования деятельности для государственных и негосударственных организаций | D12: 0 | E12: 0 | F12: 0 | G12: 0 | H12: 1 | I12: 0 | J12: 0 | K12: 0 | L12: 0 | M12: 1 | N12: 0 | O12: 1 | P12: 0
A13: 12 | B13: 12 | C13: через тарифы за фактически проведенные работы | D13: 0 | E13: 0 | F13: 1 | G13: 0 | H13: 0 | I13: 0 | J13: 0 | K13: 0 | L13: 0 | M13: 0 | N13: 0 | O13: 1 | P13: 0
... A610: 609 | B610: 271 | C610: Экономических обоснованные тарифы и подушевые нормативыэто нужно выносить на общее собрание | D610: 0 | E610: 0 | F610: 1 | G610: 0 | H610: 0 | I610: 0 | J610: 0 | K610: 0 | L610: 0 | M610: 0 | N610: 0 | O610: 1 | P610: 0

Sheet Коды
A1: № | B1: Код | C1: Название | D1: Описание | E1: Тип
A2: 1 | B2: НОРМА_442ФЗ | C2: 442-ФЗ и связанные акты | D2: Изменение/уточнение ФЗ № 442-ФЗ и связанных актов для расширения доступа НКО. | E2: тематический
A3: 2 | B3: КОНКУРС_ПРОЦЕДУРЫ | C3: Конкурсы и процедуры | D3: Упрощение конкурсов, снижение бюрократии, 44-ФЗ/223-ФЗ. | E3: тематический
A4: 3 | B4: ТАРИФЫ_НОРМАТИВЫ | C4: Тарифы и нормативы | D4: Тарифы, подушевые нормативы, индексация финансирования соцуслуг. | E4: тематический
A5: 4 | B5: РЕЕСТР_ПОСТАВЩИКОВ | C5: Реестр поставщиков | D5: Упрощение включения в реестр, прозрачные критерии. | E5: тематический
A6: 5 | B6: ГАРАНТИИ_ОБЪЕМОВ | C6: Гарантии объёмов | D6: Гарантированный объём, многолетние контракты, авансирование, лимиты. | E6: тематический
A7: 6 | B7: ОБУЧЕНИЕ_НКО | C7: Обучение НКО | D7: Обучение конкурсам, отчётности, юридическим требованиям. | E7: тематический
A8: 7 | B8: ИНФОРМАЦИЯ_ПРОЗРАЧНОСТЬ | C8: Информация и прозрачность | D8: Информирование о конкурсах, критериях, планах финансирования. | E8: тематический
A9: 8 | B9: ИНСТИТУТЫ_ПОДДЕРЖКИ | C9: Институты поддержки | D9: Ресурсные центры, опорные организации, грантовая поддержка. | E9: тематический
A10: 9 | B10: МУНИЦИПАЛЬНЫЙ_УРОВЕНЬ | C10: Муниципальный уровень | D10: Практика на муниципальном уровне, решения администраций. | E10: тематический
A11: 10 | B11: КОНКУРЕНЦИЯ_АНТИМОНОПОЛИЯ | C11: Конкуренция и антимонополия | D11: Борьба с монополией госучреждений, равные условия. | E11: тематический
A12: 11 | B12: ТОНИЧЕСКИЙ_ПОЗИТИВ | C12: Позитив | D12: Позитивная оценка мер или перспектив. | E12: тональный
A13: 12 | B13: ТОНИЧЕСКИЙ_НЕГАТИВ | C13: Негатив | D13: Критика, скепсис, описание проблем. | E13: тональный
A14: 13 | B14: ТОНИЧЕСКИЙ_СОМНЕНИЕ | C14: Сомнение | D14: Затрудняюсь ответить, неопределённость. | E14: тональный

Sheet Итоги_темы
A1: РАНЖИРОВАНИЕ ТЕМАТИЧЕСКИХ КОДОВ ПО УПОМИНАЕМОСТИ
A2: Всего высказываний в корпусе: 609 | B2: =COUNTA(Данные!A2:A610)
A4: Ранг | B4: Код | C4: Название | D4: Частота | E4: Доля | F4: Формула_проверки
A5: 1 | B5: ГАРАНТИИ_ОБЪЕМОВ | C5: Гарантии объёмов | D5: =SUM(Данные!H2:H610) | E5: =D5/$B$2 | F5: =SUM(Данные!H2:H610)
A6: 2 | B6: ТАРИФЫ_НОРМАТИВЫ | C6: Тарифы и нормативы | D6: =SUM(Данные!F2:F610) | E6: =D6/$B$2 | F6: =SUM(Данные!F2:F610)
A7: 3 | B7: ИНФОРМАЦИЯ_ПРОЗРАЧНОСТЬ | C7: Информация и прозрачность | D7: =SUM(Данные!J2:J610) | E7: =D7/$B$2 | F7: =SUM(Данные!J2:J610)
A8: 4 | B8: КОНКУРС_ПРОЦЕДУРЫ | C8: Конкурсы и процедуры | D8: =SUM(Данные!E2:E610) | E8: =D8/$B$2 | F8: =SUM(Данные!E2:E610)
A9: 5 | B9: НОРМА_442ФЗ | C9: 442-ФЗ и связанные акты | D9: =SUM(Данные!D2:D610) | E9: =D9/$B$2 | F9: =SUM(Данные!D2:D610)
A10: 6 | B10: КОНКУРЕНЦИЯ_АНТИМОНОПОЛИЯ | C10: Конкуренция и антимонополия | D10: =SUM(Данные!M2:M610) | E10: =D10/$B$2 | F10: =SUM(Данные!M2:M610)
A11: 7 | B11: РЕЕСТР_ПОСТАВЩИКОВ | C11: Реестр поставщиков | D11: =SUM(Данные!G2:G610) | E11: =D11/$B$2 | F11: =SUM(Данные!G2:G610)
A12: 8 | B12: ОБУЧЕНИЕ_НКО | C12: Обучение НКО | D12: =SUM(Данные!I2:I610) | E12: =D12/$B$2 | F12: =SUM(Данные!I2:I610)
A13: 9 | B13: ИНСТИТУТЫ_ПОДДЕРЖКИ | C13: Институты поддержки | D13: =SUM(Данные!K2:K610) | E13: =D13/$B$2 | F13: =SUM(Данные!K2:K610)
A14: 10 | B14: МУНИЦИПАЛЬНЫЙ_УРОВЕНЬ | C14: Муниципальный уровень | D14: =SUM(Данные!L2:L610) | E14: =D14/$B$2 | F14: =SUM(Данные!L2:L610)

Sheet Итоги_тональность
A1: ТОНАЛЬНОСТЬ ВЫСКАЗЫВАНИЙ
A2: =COUNTA(Данные!A2:A610)
A4: Тональность | B4: Частота | C4: Доля
A5: Позитив | B5: =SUM(Данные!N2:N610) | C5: =B5/$A$2
A6: Негатив | B6: =SUM(Данные!O2:O610) | C6: =B6/$A$2
A7: Сомнение | B7: =SUM(Данные!P2:P610) | C7: =B7/$A$2
